{
  "query": "\nSELECT \n  id,\n  name,\n  components,\n  producedQuantity,\n  unitType\nFROM final_recipes\nLIMIT 3;\n",
  "command": "mysql --batch --raw --column-names --default-character-set=utf8mb4 --host gateway03.us-east-1.prod.aws.tidbcloud.com --port 4000 --user AQnpkq2FC6cpfGo.root --database UyJAnBG4RdjFPnrCDJUrf4 --execute \nSELECT \n  id,\n  name,\n  components,\n  producedQuantity,\n  unitType\nFROM final_recipes\nLIMIT 3;\n",
  "rows": [
    {
      "id": "1ZXiXNLTLpF861aOZM_RS",
      "name": "Carne Tenders",
      "components": "\"[{\\\"type\\\":\\\"ingredient\\\",\\\"componentId\\\":\\\"pvO4mMIKWrPK2ihyo5srP\\\",\\\"componentName\\\":\\\"Tenders\\\",\\\"quantity\\\":10,\\\"unit\\\":\\\"kg\\\",\\\"pricePerUnit\\\":7.12,\\\"costType\\\":\\\"\\\"},{\\\"type\\\":\\\"ingredient\\\",\\\"componentId\\\":\\\"UjhsGMDNvCnl2fPcY2kuz\\\",\\\"componentName\\\":\\\"Latte UHT\\\",\\\"quantity\\\":1.5,\\\"unit\\\":\\\"kg\\\",\\\"pricePerUnit\\\":1.07,\\\"costType\\\":\\\"\\\"},{\\\"type\\\":\\\"ingredient\\\",\\\"componentId\\\":\\\"nfsoVnu7Rmj42reiis96v\\\",\\\"componentName\\\":\\\"Yogurt greco\\\",\\\"quantity\\\":1.5,\\\"unit\\\":\\\"kg\\\",\\\"pricePerUnit\\\":4.36,\\\"costType\\\":\\\"\\\"},{\\\"type\\\":\\\"ingredient\\\",\\\"componentId\\\":\\\"xNJn8vX9r-GIo04Ian1yd\\\",\\\"componentName\\\":\\\"Farina\\\",\\\"quantity\\\":4,\\\"unit\\\":\\\"kg\\\",\\\"pricePerUnit\\\":1.17,\\\"costType\\\":\\\"\\\"},{\\\"type\\\":\\\"ingredient\\\",\\\"componentId\\\":\\\"0TKQbZT91FRZfSZH1_LBp\\\",\\\"componentName\\\":\\\"Amido di mais\\\",\\\"quantity\\\":2,\\\"unit\\\":\\\"kg\\\",\\\"pricePerUnit\\\":2.02,\\\"costType\\\":\\\"\\\"},{\\\"type\\\":\\\"ingredient\\\",\\\"componentId\\\":\\\"AJHyMU9JKkZc01X7VHVFb\\\",\\\"componentName\\\":\\\"Uova\\\",\\\"quantity\\\":6,\\\"unit\\\":\\\"unità\\\",\\\"pricePerUnit\\\":0.24,\\\"costType\\\":\\\"\\\"},{\\\"type\\\":\\\"operation\\\",\\\"componentId\\\":\\\"\\\",\\\"componentName\\\":\\\"Cuoco\\\",\\\"quantity\\\":2.5,\\\"unit\\\":\\\"unità\\\",\\\"pricePerUnit\\\":12,\\\"costType\\\":\\\"LAVORO\\\"},{\\\"type\\\":\\\"operation\\\",\\\"componentId\\\":\\\"\\\",\\\"componentName\\\":\\\"Abbattitore\\\",\\\"quantity\\\":2,\\\"unit\\\":\\\"unità\\\",\\\"pricePerUnit\\\":1.04,\\\"costType\\\":\\\"ENERGIA\\\"}]\"",
      "producedQuantity": "370.600",
      "unitType": "u"
    },
    {
      "id": "38ihZNiKuki0_MZXFNRL6",
      "name": "Pane Bun",
      "components": "\"[{\\\"type\\\":\\\"ingredient\\\",\\\"componentId\\\":\\\"xNJn8vX9r-GIo04Ian1yd\\\",\\\"componentName\\\":\\\"Farina\\\",\\\"quantity\\\":3,\\\"unit\\\":\\\"kg\\\",\\\"pricePerUnit\\\":1.17,\\\"costType\\\":\\\"\\\"},{\\\"type\\\":\\\"ingredient\\\",\\\"componentId\\\":\\\"zNAmgvAbaKYs3KbvbDT08\\\",\\\"componentName\\\":\\\"Easy Snack CL\\\",\\\"quantity\\\":2.64,\\\"unit\\\":\\\"kg\\\",\\\"pricePerUnit\\\":5.96,\\\"costType\\\":\\\"\\\"},{\\\"type\\\":\\\"ingredient\\\",\\\"componentId\\\":\\\"qCJKKOMFAccJKmZc3ZGea\\\",\\\"componentName\\\":\\\"Fiocchi di patata\\\",\\\"quantity\\\":0.18,\\\"unit\\\":\\\"kg\\\",\\\"pricePerUnit\\\":3.72,\\\"costType\\\":\\\"\\\"},{\\\"type\\\":\\\"ingredient\\\",\\\"componentId\\\":\\\"VFlPCePcnLbx2_5tKIaQj\\\",\\\"componentName\\\":\\\"Lievito otentic\\\",\\\"quantity\\\":0.3,\\\"unit\\\":\\\"kg\\\",\\\"pricePerUnit\\\":8.82,\\\"costType\\\":\\\"\\\"},{\\\"type\\\":\\\"ingredient\\\",\\\"componentId\\\":\\\"SuOqA2HcqAe5RQOjHOenq\\\",\\\"componentName\\\":\\\"Sale\\\",\\\"quantity\\\":0.096,\\\"unit\\\":\\\"kg\\\",\\\"pricePerUnit\\\":0.3,\\\"costType\\\":\\\"\\\"},{\\\"type\\\":\\\"ingredient\\\",\\\"componentId\\\":\\\"YtHDGxaFisdNuIyPtNY0G\\\",\\\"componentName\\\":\\\"Mono e digliceridi\\\",\\\"quantity\\\":0.024,\\\"unit\\\":\\\"kg\\\",\\\"pricePerUnit\\\":22.5,\\\"costType\\\":\\\"\\\"},{\\\"type\\\":\\\"ingredient\\\",\\\"componentId\\\":\\\"q-pxz3GqnTQx9_JRZ0YqR\\\",\\\"componentName\\\":\\\"Sapore carmen\\\",\\\"quantity\\\":0.156,\\\"unit\\\":\\\"kg\\\",\\\"pricePerUnit\\\":7.42,\\\"costType\\\":\\\"\\\"},{\\\"type\\\":\\\"ingredient\\\",\\\"componentId\\\":\\\"FuGZtr1Ivq9UEVdfxUF63\\\",\\\"componentName\\\":\\\"Latte di soja\\\",\\\"quantity\\\":1.5,\\\"unit\\\":\\\"kg\\\",\\\"pricePerUnit\\\":0,\\\"costType\\\":\\\"\\\"},{\\\"type\\\":\\\"ingredient\\\",\\\"componentId\\\":\\\"w6Goo2jSCBOLl1FUq2KL3\\\",\\\"componentName\\\":\\\"Acqua\\\",\\\"quantity\\\":1.5,\\\"unit\\\":\\\"kg\\\",\\\"pricePerUnit\\\":0,\\\"costType\\\":\\\"\\\"},{\\\"type\\\":\\\"ingredient\\\",\\\"componentId\\\":\\\"zgFIe9bPgtqlIB9r23Md9\\\",\\\"componentName\\\":\\\"Margarina\\\",\\\"quantity\\\":0.78,\\\"unit\\\":\\\"kg\\\",\\\"pricePerUnit\\\":4.78,\\\"costType\\\":\\\"\\\"},{\\\"type\\\":\\\"operation\\\",\\\"componentId\\\":\\\"\\\",\\\"componentName\\\":\\\"Cuoco\\\",\\\"quantity\\\":1,\\\"unit\\\":\\\"unità\\\",\\\"pricePerUnit\\\":12,\\\"costType\\\":\\\"LAVORO\\\"},{\\\"type\\\":\\\"operation\\\",\\\"componentId\\\":\\\"\\\",\\\"componentName\\\":\\\"Forno\\\",\\\"quantity\\\":0.66,\\\"unit\\\":\\\"unità\\\",\\\"pricePerUnit\\\":2.78,\\\"costType\\\":\\\"ENERGIA\\\"},{\\\"type\\\":\\\"operation\\\",\\\"componentId\\\":\\\"\\\",\\\"componentName\\\":\\\"Lievitatore\\\",\\\"quantity\\\":20,\\\"unit\\\":\\\"unità\\\",\\\"pricePerUnit\\\":0.17,\\\"costType\\\":\\\"ENERGIA\\\"},{\\\"type\\\":\\\"operation\\\",\\\"componentId\\\":\\\"\\\",\\\"componentName\\\":\\\"Arrotondatrice\\\",\\\"quantity\\\":0.5,\\\"unit\\\":\\\"unità\\\",\\\"pricePerUnit\\\":0.5,\\\"costType\\\":\\\"ENERGIA\\\"},{\\\"type\\\":\\\"operation\\\",\\\"componentId\\\":\\\"\\\",\\\"componentName\\\":\\\"Impastatrice\\\",\\\"quantity\\\":0.33,\\\"unit\\\":\\\"unità\\\",\\\"pricePerUnit\\\":0.89,\\\"costType\\\":\\\"ENERGIA\\\"}]\"",
      "producedQuantity": "90.000",
      "unitType": "k"
    },
    {
      "id": "3RY7r6ujhRES0KwmjHbb9",
      "name": "Salsa Memphis",
      "components": "[{\"componentId\": \"sX0KY6rxgs8rzey8pFX--\", \"componentName\": \"Senape\", \"quantity\": 0.02, \"type\": \"ingredient\", \"unit\": \"kg\"}, {\"componentId\": \"BGtpWHKEblWCiK6F0szR5\", \"componentName\": \"Zucchero invertito\", \"quantity\": 0.05, \"type\": \"ingredient\", \"unit\": \"kg\"}, {\"componentId\": \"BfM0cgLmN22IyidrAk5iq\", \"componentName\": \"Fondo bruno vegano\", \"quantity\": 0.03, \"type\": \"ingredient\", \"unit\": \"kg\"}, {\"componentId\": \"2rF5VwzkcOtanlqhNrv4Y\", \"componentName\": \"Salsa ketchup\", \"quantity\": 0.2, \"type\": \"semi_finished\", \"unit\": \"kg\"}, {\"componentId\": \"9WQvqdGlWFZnk7yV8gQnt\", \"componentName\": \"Xantana\", \"quantity\": 0.00025, \"type\": \"ingredient\", \"unit\": \"kg\"}, {\"componentId\": \"E_lg2LmUumGJoBlx6ReY_\", \"componentName\": \"Amido pregelatinizzato\", \"quantity\": 0.00025, \"type\": \"ingredient\", \"unit\": \"kg\"}]",
      "producedQuantity": "0.000",
      "unitType": "k"
    }
  ],
  "messages": [],
  "stdout": "id\tname\tcomponents\tproducedQuantity\tunitType\n1ZXiXNLTLpF861aOZM_RS\tCarne Tenders\t\"[{\\\"type\\\":\\\"ingredient\\\",\\\"componentId\\\":\\\"pvO4mMIKWrPK2ihyo5srP\\\",\\\"componentName\\\":\\\"Tenders\\\",\\\"quantity\\\":10,\\\"unit\\\":\\\"kg\\\",\\\"pricePerUnit\\\":7.12,\\\"costType\\\":\\\"\\\"},{\\\"type\\\":\\\"ingredient\\\",\\\"componentId\\\":\\\"UjhsGMDNvCnl2fPcY2kuz\\\",\\\"componentName\\\":\\\"Latte UHT\\\",\\\"quantity\\\":1.5,\\\"unit\\\":\\\"kg\\\",\\\"pricePerUnit\\\":1.07,\\\"costType\\\":\\\"\\\"},{\\\"type\\\":\\\"ingredient\\\",\\\"componentId\\\":\\\"nfsoVnu7Rmj42reiis96v\\\",\\\"componentName\\\":\\\"Yogurt greco\\\",\\\"quantity\\\":1.5,\\\"unit\\\":\\\"kg\\\",\\\"pricePerUnit\\\":4.36,\\\"costType\\\":\\\"\\\"},{\\\"type\\\":\\\"ingredient\\\",\\\"componentId\\\":\\\"xNJn8vX9r-GIo04Ian1yd\\\",\\\"componentName\\\":\\\"Farina\\\",\\\"quantity\\\":4,\\\"unit\\\":\\\"kg\\\",\\\"pricePerUnit\\\":1.17,\\\"costType\\\":\\\"\\\"},{\\\"type\\\":\\\"ingredient\\\",\\\"componentId\\\":\\\"0TKQbZT91FRZfSZH1_LBp\\\",\\\"componentName\\\":\\\"Amido di mais\\\",\\\"quantity\\\":2,\\\"unit\\\":\\\"kg\\\",\\\"pricePerUnit\\\":2.02,\\\"costType\\\":\\\"\\\"},{\\\"type\\\":\\\"ingredient\\\",\\\"componentId\\\":\\\"AJHyMU9JKkZc01X7VHVFb\\\",\\\"componentName\\\":\\\"Uova\\\",\\\"quantity\\\":6,\\\"unit\\\":\\\"unità\\\",\\\"pricePerUnit\\\":0.24,\\\"costType\\\":\\\"\\\"},{\\\"type\\\":\\\"operation\\\",\\\"componentId\\\":\\\"\\\",\\\"componentName\\\":\\\"Cuoco\\\",\\\"quantity\\\":2.5,\\\"unit\\\":\\\"unità\\\",\\\"pricePerUnit\\\":12,\\\"costType\\\":\\\"LAVORO\\\"},{\\\"type\\\":\\\"operation\\\",\\\"componentId\\\":\\\"\\\",\\\"componentName\\\":\\\"Abbattitore\\\",\\\"quantity\\\":2,\\\"unit\\\":\\\"unità\\\",\\\"pricePerUnit\\\":1.04,\\\"costType\\\":\\\"ENERGIA\\\"}]\"\t370.600\tu\n38ihZNiKuki0_MZXFNRL6\tPane Bun\t\"[{\\\"type\\\":\\\"ingredient\\\",\\\"componentId\\\":\\\"xNJn8vX9r-GIo04Ian1yd\\\",\\\"componentName\\\":\\\"Farina\\\",\\\"quantity\\\":3,\\\"unit\\\":\\\"kg\\\",\\\"pricePerUnit\\\":1.17,\\\"costType\\\":\\\"\\\"},{\\\"type\\\":\\\"ingredient\\\",\\\"componentId\\\":\\\"zNAmgvAbaKYs3KbvbDT08\\\",\\\"componentName\\\":\\\"Easy Snack CL\\\",\\\"quantity\\\":2.64,\\\"unit\\\":\\\"kg\\\",\\\"pricePerUnit\\\":5.96,\\\"costType\\\":\\\"\\\"},{\\\"type\\\":\\\"ingredient\\\",\\\"componentId\\\":\\\"qCJKKOMFAccJKmZc3ZGea\\\",\\\"componentName\\\":\\\"Fiocchi di patata\\\",\\\"quantity\\\":0.18,\\\"unit\\\":\\\"kg\\\",\\\"pricePerUnit\\\":3.72,\\\"costType\\\":\\\"\\\"},{\\\"type\\\":\\\"ingredient\\\",\\\"componentId\\\":\\\"VFlPCePcnLbx2_5tKIaQj\\\",\\\"componentName\\\":\\\"Lievito otentic\\\",\\\"quantity\\\":0.3,\\\"unit\\\":\\\"kg\\\",\\\"pricePerUnit\\\":8.82,\\\"costType\\\":\\\"\\\"},{\\\"type\\\":\\\"ingredient\\\",\\\"componentId\\\":\\\"SuOqA2HcqAe5RQOjHOenq\\\",\\\"componentName\\\":\\\"Sale\\\",\\\"quantity\\\":0.096,\\\"unit\\\":\\\"kg\\\",\\\"pricePerUnit\\\":0.3,\\\"costType\\\":\\\"\\\"},{\\\"type\\\":\\\"ingredient\\\",\\\"componentId\\\":\\\"YtHDGxaFisdNuIyPtNY0G\\\",\\\"componentName\\\":\\\"Mono e digliceridi\\\",\\\"quantity\\\":0.024,\\\"unit\\\":\\\"kg\\\",\\\"pricePerUnit\\\":22.5,\\\"costType\\\":\\\"\\\"},{\\\"type\\\":\\\"ingredient\\\",\\\"componentId\\\":\\\"q-pxz3GqnTQx9_JRZ0YqR\\\",\\\"componentName\\\":\\\"Sapore carmen\\\",\\\"quantity\\\":0.156,\\\"unit\\\":\\\"kg\\\",\\\"pricePerUnit\\\":7.42,\\\"costType\\\":\\\"\\\"},{\\\"type\\\":\\\"ingredient\\\",\\\"componentId\\\":\\\"FuGZtr1Ivq9UEVdfxUF63\\\",\\\"componentName\\\":\\\"Latte di soja\\\",\\\"quantity\\\":1.5,\\\"unit\\\":\\\"kg\\\",\\\"pricePerUnit\\\":0,\\\"costType\\\":\\\"\\\"},{\\\"type\\\":\\\"ingredient\\\",\\\"componentId\\\":\\\"w6Goo2jSCBOLl1FUq2KL3\\\",\\\"componentName\\\":\\\"Acqua\\\",\\\"quantity\\\":1.5,\\\"unit\\\":\\\"kg\\\",\\\"pricePerUnit\\\":0,\\\"costType\\\":\\\"\\\"},{\\\"type\\\":\\\"ingredient\\\",\\\"componentId\\\":\\\"zgFIe9bPgtqlIB9r23Md9\\\",\\\"componentName\\\":\\\"Margarina\\\",\\\"quantity\\\":0.78,\\\"unit\\\":\\\"kg\\\",\\\"pricePerUnit\\\":4.78,\\\"costType\\\":\\\"\\\"},{\\\"type\\\":\\\"operation\\\",\\\"componentId\\\":\\\"\\\",\\\"componentName\\\":\\\"Cuoco\\\",\\\"quantity\\\":1,\\\"unit\\\":\\\"unità\\\",\\\"pricePerUnit\\\":12,\\\"costType\\\":\\\"LAVORO\\\"},{\\\"type\\\":\\\"operation\\\",\\\"componentId\\\":\\\"\\\",\\\"componentName\\\":\\\"Forno\\\",\\\"quantity\\\":0.66,\\\"unit\\\":\\\"unità\\\",\\\"pricePerUnit\\\":2.78,\\\"costType\\\":\\\"ENERGIA\\\"},{\\\"type\\\":\\\"operation\\\",\\\"componentId\\\":\\\"\\\",\\\"componentName\\\":\\\"Lievitatore\\\",\\\"quantity\\\":20,\\\"unit\\\":\\\"unità\\\",\\\"pricePerUnit\\\":0.17,\\\"costType\\\":\\\"ENERGIA\\\"},{\\\"type\\\":\\\"operation\\\",\\\"componentId\\\":\\\"\\\",\\\"componentName\\\":\\\"Arrotondatrice\\\",\\\"quantity\\\":0.5,\\\"unit\\\":\\\"unità\\\",\\\"pricePerUnit\\\":0.5,\\\"costType\\\":\\\"ENERGIA\\\"},{\\\"type\\\":\\\"operation\\\",\\\"componentId\\\":\\\"\\\",\\\"componentName\\\":\\\"Impastatrice\\\",\\\"quantity\\\":0.33,\\\"unit\\\":\\\"unità\\\",\\\"pricePerUnit\\\":0.89,\\\"costType\\\":\\\"ENERGIA\\\"}]\"\t90.000\tk\n3RY7r6ujhRES0KwmjHbb9\tSalsa Memphis\t[{\"componentId\": \"sX0KY6rxgs8rzey8pFX--\", \"componentName\": \"Senape\", \"quantity\": 0.02, \"type\": \"ingredient\", \"unit\": \"kg\"}, {\"componentId\": \"BGtpWHKEblWCiK6F0szR5\", \"componentName\": \"Zucchero invertito\", \"quantity\": 0.05, \"type\": \"ingredient\", \"unit\": \"kg\"}, {\"componentId\": \"BfM0cgLmN22IyidrAk5iq\", \"componentName\": \"Fondo bruno vegano\", \"quantity\": 0.03, \"type\": \"ingredient\", \"unit\": \"kg\"}, {\"componentId\": \"2rF5VwzkcOtanlqhNrv4Y\", \"componentName\": \"Salsa ketchup\", \"quantity\": 0.2, \"type\": \"semi_finished\", \"unit\": \"kg\"}, {\"componentId\": \"9WQvqdGlWFZnk7yV8gQnt\", \"componentName\": \"Xantana\", \"quantity\": 0.00025, \"type\": \"ingredient\", \"unit\": \"kg\"}, {\"componentId\": \"E_lg2LmUumGJoBlx6ReY_\", \"componentName\": \"Amido pregelatinizzato\", \"quantity\": 0.00025, \"type\": \"ingredient\", \"unit\": \"kg\"}]\t0.000\tk\n",
  "stderr": "",
  "execution_time_ms": 60
}